[
  {
    "id": "directors",
    "name": "Directors",
    "field": "directors",
    "aggregation": "directors.keyword",
    "query": "directors:*",
    "categoryQuery": "",
    "script": "",
    "domain": "movie"
  },
  {
    "id": "producers",
    "name": "Producers",
    "field": "producers",
    "aggregation": "producers.keyword",
    "query": "producers:*",
    "categoryQuery": "",
    "script": "",
    "domain": "movie"
  },
  {
    "id": "writers",
    "name": "Writers",
    "field": "writers",
    "aggregation": "writers.keyword",
    "query": "writers:*",
    "categoryQuery": "",
    "script": "",
    "domain": "movie"
  },
  {
    "id": "cast",
    "name": "Cast",
    "field": "cast",
    "aggregation": "cast.keyword",
    "query": "cast:*",
    "categoryQuery": "",
    "script": "",
    "domain": "movie"
  },
  {
    "id": "year",
    "name": "Year",
    "field": "year",
    "aggregation": "year",
    "query": "year:*",
    "categoryQuery": "",
    "script": "",
    "domain": "movie"
  },
  {
    "id": "genres",
    "name": "Genres",
    "field": "genres",
    "aggregation": "genres.keyword",
    "query": "genres:*",
    "categoryQuery": "",
    "script": "",
    "domain": "movie"
  },
  {
    "id": "languages",
    "name": "Language",
    "field": "languages",
    "aggregation": "languages.keyword",
    "query": "languages:*",
    "categoryQuery": "",
    "script": "",
    "domain": "movie"
  },
  {
    "id": "country",
    "name": "Country",
    "field": "country",
    "aggregation": "country.keyword",
    "query": "country:*",
    "categoryQuery": "",
    "script": "",
    "domain": "movie"
  },
  {
    "id": "rotten_tomatoes_score",
    "name": "Rotten Tomatoes",
    "field": "rotten_tomatoes_score",
    "aggregation": "rotten_tomatoes_score",
    "query": "rotten_tomatoes_score:*",
    "categoryQuery": "",
    "script": "",
    "domain": "movie"
  }
]
